core/__init__.py
core/deployment.py
core/flow_builder.py
core/model_integration.py
core/training.py
chatbot_studio-1.0.7.dist-info/LICENSE.txt
chatbot_studio-1.0.7.dist-info/METADATA
chatbot_studio-1.0.7.dist-info/WHEEL
chatbot_studio-1.0.7.dist-info/top_level.txt
chatbot_studio-1.0.7.dist-info/RECORD
