Metadata-Version: 2.2
Name: chatbot_studio
Version: 1.0.7
Summary: A framework to design, train, and deploy AI chatbots.
Home-page: https://github.com/gopalakrishnanarjun/chatbot_studio
Author: Gopalakrishnan Arjunan
Author-email: gopalakrishnana02@gmail.com
Classifier: Programming Language :: Python :: 3
Classifier: License :: OSI Approved :: MIT License
Classifier: Operating System :: OS Independent
Requires-Python: >=3.8
License-File: LICENSE.txt
Requires-Dist: transformers>=4.0
Requires-Dist: torch>=1.7
Requires-Dist: flask>=2.0
Requires-Dist: python-telegram-bot
Requires-Dist: slack_sdk
Requires-Dist: twilio
Dynamic: author
Dynamic: author-email
Dynamic: classifier
Dynamic: description
Dynamic: description-content-type
Dynamic: home-page
Dynamic: requires-dist
Dynamic: requires-python
Dynamic: summary
